apix/__init__.py
apix/__main__.py
apix/cli.py
apix-0.0.0.dist-info/WHEEL
apix-0.0.0.dist-info/METADATA
apix-0.0.0.dist-info/RECORD
